regain/__init__.py
regain/clustering.py
regain/discriminant_analysis.py
regain/math.py
regain/norm.py
regain/prox.py
regain/scores.py
regain/update_rules.py
regain/utils.py
regain/validation.py
regain/bayesian/__init__.py
regain/bayesian/_laplace_approximation.py
regain/bayesian/gaussian_process_.py
regain/bayesian/gwishart_inference.py
regain/bayesian/sampling.py
regain/bayesian/stats.py
regain/bayesian/wishart_distribution_.py
regain/bayesian/wishart_process_.py
regain/covariance/__init__.py
regain/covariance/graphical_lasso_.py
regain/covariance/infimal_convolution_.py
regain/covariance/kernel_latent_time_graphical_lasso_.py
regain/covariance/kernel_time_graphical_lasso_.py
regain/covariance/latent_graphical_lasso_.py
regain/covariance/latent_time_graphical_lasso_.py
regain/covariance/latent_time_matrix_decomposition.py
regain/covariance/missing_graphical_lasso_.py
regain/covariance/time_graphical_lasso_.py
regain/data/__init__.py
regain/data/base.py
regain/datasets/__init__.py
regain/datasets/base.py
regain/datasets/gaussian.py
regain/datasets/ising.py
regain/datasets/kernels.py
regain/datasets/multi_class.py
regain/datasets/poisson.py
regain/forward_backward/__init__.py
regain/forward_backward/forward_backward.py
regain/forward_backward/time_graphical_lasso_.py
regain/generalized_linear_model/__init__.py
regain/generalized_linear_model/base.py
regain/generalized_linear_model/glm_gaussian.py
regain/generalized_linear_model/glm_ising.py
regain/generalized_linear_model/glm_poisson.py
regain/generalized_linear_model/glm_time_ising.py
regain/generalized_linear_model/glm_time_poisson.py
regain/linear_model/__init__.py
regain/linear_model/_group_lasso_overlap_old_.py
regain/linear_model/group_lasso_.py
regain/linear_model/group_lasso_overlap_.py
regain/linear_model/lasso_.py
regain/model_selection/__init__.py
regain/model_selection/_bayesian_optimization.py
regain/model_selection/stability_optimization.py
regain/plotting/__init__.py
regain/plotting/covariance.py
regain-0.3.9.dist-info/AUTHORS.txt
regain-0.3.9.dist-info/LICENSE
regain-0.3.9.dist-info/METADATA
regain-0.3.9.dist-info/WHEEL
regain-0.3.9.dist-info/top_level.txt
regain-0.3.9.dist-info/RECORD
