Metadata-Version: 2.1
Name: regain
Version: 0.3.9
Summary: REGAIN (Regularised Graph Inference)
Home-page: https://github.com/fdtomasi/regain
Download-URL: https://github.com/fdtomasi/regain/archive/v0.3.9.tar.gz
Author: Federico Tomasi
Author-email: fdtomasi@gmail.com
Maintainer: Federico Tomasi
Maintainer-email: fdtomasi@gmail.com
License: FreeBSD
Keywords: graph inference,latent variables
Classifier: Development Status :: 4 - Beta
Classifier: Environment :: Console
Classifier: Intended Audience :: Science/Research
Classifier: Intended Audience :: Developers
Classifier: Programming Language :: Python
Classifier: License :: OSI Approved :: BSD License
Classifier: Topic :: Software Development
Classifier: Topic :: Scientific/Engineering
Classifier: Natural Language :: English
Classifier: Operating System :: POSIX
Classifier: Operating System :: Unix
Classifier: Operating System :: MacOS
Classifier: Programming Language :: Python
License-File: LICENSE
License-File: AUTHORS.txt
